pySWXF/AuI_funs.py
pySWXF/Br_funs.py
pySWXF/NM_clean_NIU_NOKW_Mar26_24_fit4.json
pySWXF/__init__.py
pySWXF/bilayer_model.py
pySWXF/bilayer_model_july24.py
pySWXF/fit_simple_surface.ipynb
pySWXF/fluor_fit.py
pySWXF/niu_multilayer_fit_params_3_LBL.json
pySWXF/refl_funs.py
pySWXF/spec_utils.py
pySWXF/xray_utils.py
pyswxf-1.0.7.dist-info/METADATA
pyswxf-1.0.7.dist-info/WHEEL
pyswxf-1.0.7.dist-info/licenses/LICENSE
pyswxf-1.0.7.dist-info/RECORD
