Metadata-Version: 2.1
Name: pySWXF
Version: 1.0.7
Summary: Routines for calculating standing wave x-ray fluorescence and x-ray reflectivity
Project-URL: Homepage, https://github.com/pypa/pySWXF
Project-URL: Bug Tracker, https://github.com/pypa/pySWXF/issues
Author-email: Laurence Lurio <llurio@niu.edu>
License-File: LICENSE
Classifier: License :: OSI Approved :: MIT License
Classifier: Operating System :: OS Independent
Classifier: Programming Language :: Python :: 3
Requires-Python: >3.7
